fabric_lakehouse_mcp-0.3.13.dist-info/licenses/LICENSE
fabric_rti_mcp/__init__.py
fabric_rti_mcp/_version.py
fabric_rti_mcp/common.py
fabric_rti_mcp/mcp-manifest.json
fabric_rti_mcp/server.py
fabric_rti_mcp/authentication/auth_middleware.py
fabric_rti_mcp/authentication/token_obo_exchanger.py
fabric_rti_mcp/config/obo_config.py
fabric_rti_mcp/tools/lakehouse_sql_mcp_tools.py
fabric_rti_mcp/tools/lakehouse_sql_tool.py
fabric_rti_mcp/tools/query_history_mcp_tools.py
fabric_rti_mcp/tools/query_history_tool.py
fabric_rti_mcp/utils/__init__.py
fabric_rti_mcp/utils/fabric_api_http_client.py
fabric_lakehouse_mcp-0.3.13.dist-info/METADATA
fabric_lakehouse_mcp-0.3.13.dist-info/WHEEL
fabric_lakehouse_mcp-0.3.13.dist-info/entry_points.txt
fabric_lakehouse_mcp-0.3.13.dist-info/top_level.txt
fabric_lakehouse_mcp-0.3.13.dist-info/RECORD
