Metadata-Version: 2.4
Name: fabric-lakehouse-mcp
Version: 0.3.13
Summary: Microsoft Fabric Lakehouse MCP Server - SQL analytics tools for AI agents
License: MIT
Project-URL: Homepage, https://github.com/melisa-l/fabric-rti-mcp
Project-URL: Repository, https://github.com/melisa-l/fabric-rti-mcp
Project-URL: Issues, https://github.com/melisa-l/fabric-rti-mcp/issues
Project-URL: Documentation, https://github.com/melisa-l/fabric-rti-mcp#readme
Keywords: mcp,model-context-protocol,microsoft-fabric,lakehouse,sql
Classifier: Programming Language :: Python :: 3.10
Classifier: Programming Language :: Python :: 3.11
Classifier: Programming Language :: Python :: 3.12
Classifier: Programming Language :: Python :: 3.13
Classifier: Operating System :: OS Independent
Classifier: Development Status :: 3 - Alpha
Classifier: Topic :: Software Development :: Libraries :: Python Modules
Requires-Python: >=3.10
License-File: LICENSE
Requires-Dist: httpx~=0.28.1
Requires-Dist: fastmcp~=2.5.0
Requires-Dist: azure-identity~=1.23.0
Requires-Dist: msal~=1.32.0
Requires-Dist: pyodbc>=5.0.0
Provides-Extra: dev
Requires-Dist: black>=23.0.0; extra == "dev"
Requires-Dist: isort>=5.12.0; extra == "dev"
Requires-Dist: flake8>=6.0.0; extra == "dev"
Requires-Dist: mypy>=1.0.0; extra == "dev"
Requires-Dist: pytest>=7.0.0; extra == "dev"
Provides-Extra: clipboard
Requires-Dist: pyperclip>=1.8.0; extra == "clipboard"
Dynamic: license-file
